ploomby/__init__.py
ploomby/abc/__init__.py
ploomby/abc/consumer.py
ploomby/abc/exceptions.py
ploomby/abc/factory.py
ploomby/abc/types.py
ploomby/logger.py
ploomby/rabbit/__init__.py
ploomby/rabbit/consumer.py
ploomby/rabbit/factory.py
ploomby/registry.py
ploomby-0.1.5.dist-info/METADATA
ploomby-0.1.5.dist-info/WHEEL
ploomby-0.1.5.dist-info/RECORD
