Metadata-Version: 2.4
Name: ploomby
Version: 0.1.5
Summary: 
Author: TheAppleKingy
Author-email: pridanov.ali.job@gmail.com
Requires-Python: >=3.13,<4.0
Classifier: Programming Language :: Python :: 3
Classifier: Programming Language :: Python :: 3.13
Classifier: Programming Language :: Python :: 3.14
Requires-Dist: aio-pika (>=9.5.8,<10.0.0)
Requires-Dist: loguru (>=0.7.3,<0.8.0)
Requires-Dist: pydantic[email] (>=2.12.5,<3.0.0)
